pickledb.py
pickledb-1.5.dist-info/licenses/LICENSE
pickledb-1.5.dist-info/WHEEL
pickledb-1.5.dist-info/METADATA
pickledb-1.5.dist-info/RECORD
