Metadata-Version: 2.4
Name: pickledb
Version: 1.5
Summary: An in-memory key-value store using orjson.
Keywords: pickle,database,json,redis,asyncio,sqlite
Author-email: Harrison Erd <harrisonerd@gmail.com>
Requires-Python: >=3.10
Classifier: Framework :: AsyncIO
Classifier: Programming Language :: Python :: 3
Classifier: Intended Audience :: Developers
Classifier: Programming Language :: Python
Classifier: License :: OSI Approved :: BSD License
Classifier: Intended Audience :: Developers
Classifier: Topic :: Database
License-File: LICENSE
Requires-Dist: orjson
Requires-Dist: aiofiles
Requires-Dist: aiosqlite ; extra == "sqlite"
Project-URL: Homepage, https://patx.github.io/pickledb
Project-URL: Repository, https://github.com/patx/pickledb
Provides-Extra: sqlite
